text_alignment_tool/.git
text_alignment_tool/__init__.py
text_alignment_tool/alignment_algorithms/__init__.py
text_alignment_tool/alignment_algorithms/alignment_algorithm.py
text_alignment_tool/alignment_algorithms/chunk_alignment.py
text_alignment_tool/alignment_algorithms/global_alignment.py
text_alignment_tool/alignment_algorithms/local_alignment.py
text_alignment_tool/alignment_algorithms/needle_in_haystack_alignment.py
text_alignment_tool/alignment_tool/__init__.py
text_alignment_tool/alignment_tool/aligner.py
text_alignment_tool/alignment_tool/alignment_tool.py
text_alignment_tool/analyzers/__init__.py
text_alignment_tool/analyzers/analysis_helpers.py
text_alignment_tool/find_wordlist_for_alignment/__init__.py
text_alignment_tool/find_wordlist_for_alignment/find_wordlist_for_alignment.py
text_alignment_tool/shared_classes/__init__.py
text_alignment_tool/shared_classes/shared_classes.py
text_alignment_tool/text_loaders/__init__.py
text_alignment_tool/text_loaders/alto_xml_loader.py
text_alignment_tool/text_loaders/newline_separated_text_loader.py
text_alignment_tool/text_loaders/string_text_loader.py
text_alignment_tool/text_loaders/text_loader.py
text_alignment_tool/text_transformers/__init__.py
text_alignment_tool/text_transformers/consistent_bracketing_transformer.py
text_alignment_tool/text_transformers/remove_character_transformer.py
text_alignment_tool/text_transformers/remove_enclosed_transformer.py
text_alignment_tool/text_transformers/substitute_character_transformer.py
text_alignment_tool/text_transformers/substitute_multiple_characters_transform.py
text_alignment_tool/text_transformers/text_transformer.py
text_alignment_tool-0.2.15.dist-info/LICENSE
text_alignment_tool-0.2.15.dist-info/WHEEL
text_alignment_tool-0.2.15.dist-info/METADATA
text_alignment_tool-0.2.15.dist-info/RECORD
