Metadata-Version: 2.1
Name: text-alignment-tool
Version: 0.2.15
Summary: A tool for performing complex text alignment processes.
Home-page: https://gitlab.com/sofer_mahir/text_alignment_tool
License: MIT
Keywords: alignment,needleman,wunsch,pipeline
Author: Bronson Brown-deVost
Author-email: bronsonbdevost@gmail.com
Requires-Python: >=3.7.1,<3.11
Classifier: License :: OSI Approved :: MIT License
Classifier: Programming Language :: Python :: 3
Classifier: Programming Language :: Python :: 3.8
Classifier: Programming Language :: Python :: 3.9
Requires-Dist: bidict (>=0.21.4,<0.22.0)
Requires-Dist: cursive-re (>=0.0.4,<0.0.5)
Requires-Dist: dotmap (>=1.3.26,<2.0.0)
Requires-Dist: edlib (>=1.3.9,<2.0.0)
Requires-Dist: fuzzywuzzy (>=0.18.0,<0.19.0)
Requires-Dist: lxml (>=4.7.1,<5.0.0)
Requires-Dist: minineedle (>=3.0.0,<4.0.0)
Requires-Dist: numpy (>=1.21.4,<2.0.0)
Requires-Dist: pandas (>=1.3.5,<2.0.0)
Requires-Dist: python-Levenshtein (>=0.12.2,<0.13.0)
Requires-Dist: swalign (>=0.3.6,<0.4.0)
Requires-Dist: terminaltables (>=3.1.10,<4.0.0)
Project-URL: Repository, https://gitlab.com/sofer_mahir/text_alignment_tool
Project-URL: issues, https://gitlab.com/sofer_mahir/text_alignment_tool/issues
